tccli/__init__.py
tccli/argparser.py
tccli/argument.py
tccli/base_command.py
tccli/cli_input_json.py
tccli/cli_unfold_argument.py
tccli/command.py
tccli/completer.py
tccli/configure.py
tccli/credentials.py
tccli/document_handler.py
tccli/error_msg.py
tccli/exceptions.py
tccli/format_output.py
tccli/generatecliskeleton.py
tccli/help_command.py
tccli/loaders.py
tccli/log.py
tccli/main.py
tccli/oauth.py
tccli/options_define.py
tccli/plugin.py
tccli/sso.py
tccli/style.py
tccli/table.py
tccli/text.py
tccli/utils.py
tccli/advance/__init__.py
tccli/advance/userConfigHandler.py
tccli/advance/userProfileHandler.py
tccli/colorama/__init__.py
tccli/colorama/ansi.py
tccli/colorama/ansitowin32.py
tccli/colorama/initialise.py
tccli/colorama/win32.py
tccli/colorama/winterm.py
tccli/plugins/__init__.py
tccli/plugins/auth/__init__.py
tccli/plugins/auth/browser_flow.py
tccli/plugins/auth/login.py
tccli/plugins/auth/logout.py
tccli/plugins/auth/texts.py
tccli/plugins/sso/__init__.py
tccli/plugins/sso/configs.py
tccli/plugins/sso/configure.py
tccli/plugins/sso/login.py
tccli/plugins/sso/logout.py
tccli/plugins/sso/terminal.py
tccli/plugins/sso/texts.py
tccli/plugins/test/__init__.py
tccli/plugins/test/add.py
tccli/services/__init__.py
tccli/services/advisor/__init__.py
tccli/services/advisor/advisor_client.py
tccli/services/advisor/v20200721/api.json
tccli/services/advisor/v20200721/examples.json
tccli/services/ai3d/__init__.py
tccli/services/ai3d/ai3d_client.py
tccli/services/ai3d/v20250513/api.json
tccli/services/ai3d/v20250513/examples.json
tccli/services/aiart/__init__.py
tccli/services/aiart/aiart_client.py
tccli/services/aiart/v20221229/api.json
tccli/services/aiart/v20221229/examples.json
tccli/services/ams/__init__.py
tccli/services/ams/ams_client.py
tccli/services/ams/v20201229/api.json
tccli/services/ams/v20201229/examples.json
tccli/services/antiddos/__init__.py
tccli/services/antiddos/antiddos_client.py
tccli/services/antiddos/v20200309/api.json
tccli_intl_en-3.1.40.1.dist-info/LICENSE
tccli_intl_en-3.1.40.1.dist-info/METADATA
tccli_intl_en-3.1.40.1.dist-info/WHEEL
tccli_intl_en-3.1.40.1.dist-info/entry_points.txt
tccli_intl_en-3.1.40.1.dist-info/top_level.txt
tccli_intl_en-3.1.40.1.dist-info/RECORD
