Metadata-Version: 2.1
Name: tccli-intl-en
Version: 3.1.40.1
Summary: Universal Command Line Environment for Tencent Cloud
Home-page: https://github.com/TencentCloud/tencentcloud-cli-intl-en.git
Author: Tencent Cloud
Maintainer-email: TencentCloudApi@tencent.com
Platform: unix
Platform: linux
Platform: win64
Classifier: Development Status :: 5 - Production/Stable
Classifier: Intended Audience :: Developers
Classifier: License :: OSI Approved :: Apache Software License
Classifier: Programming Language :: Python
Classifier: Programming Language :: Python :: 2.7
Classifier: Programming Language :: Python :: 3
Classifier: Programming Language :: Python :: 3.1
Classifier: Programming Language :: Python :: 3.2
Classifier: Programming Language :: Python :: 3.3
Classifier: Programming Language :: Python :: 3.4
Classifier: Programming Language :: Python :: 3.5
Classifier: Programming Language :: Python :: 3.6
License-File: LICENSE
Requires-Dist: tencentcloud-sdk-python-intl-en >=3.1.40
Requires-Dist: jmespath ==0.10.0
Requires-Dist: six ==1.16.0
